{"frameRate":24,"isGlobal":0,"armature":[{"ik":[],"type":"Armature","bone":[{"name":"root","transform":{}},{"length":124,"transform":{"y":103.3,"skX":66.8105,"skY":66.8105,"x":-35.35},"parent":"root","name":"leg_right"},{"length":92,"transform":{"scX":0.65,"y":-12.2089,"skX":0.8371,"skY":0.8371,"x":-34},"parent":"root","name":"braco"},{"length":243,"transform":{"y":101.95,"skX":-101.9409,"skY":-101.9409,"x":16.3},"parent":"root","name":"hearth_2"},{"length":94,"transform":{"y":88.35,"skX":67.1163,"skY":67.1163,"x":66.55},"parent":"root","name":"leg_left"},{"length":119,"transform":{"y":-10.8589,"skX":-6.5608,"skY":-6.5608,"x":21.7101},"parent":"root","name":"punho"},{"length":239,"transform":{"y":105.1,"skX":-113.5787,"skY":-113.5787,"x":-7.75},"parent":"root","name":"hearth_1"}],"aabb":{"width":479.5005827592098,"y":-218.0020279451668,"height":542.0020279451668,"x":-304.0005827592098},"slot":[{"color":{},"name":"leg_left","parent":"leg_left"},{"z":1,"color":{},"name":"hearth_2","parent":"hearth_2","displayIndex":1},{"z":2,"color":{},"name":"braco","parent":"braco"},{"z":3,"color":{},"name":"punho","parent":"punho"},{"z":4,"color":{},"name":"hearth_1","parent":"hearth_1","displayIndex":1},{"z":5,"color":{},"name":"leg_right","parent":"leg_right"}],"animation":[{"duration":8,"frame":[],"bone":[{"frame":[{"duration":8,"transform":{}}],"name":"root"},{"frame":[{"duration":4,"transform":{},"tweenEasing":0},{"duration":4,"transform":{"scX":0.8,"y":34.3947,"x":10.5889},"tweenEasing":0},{"duration":0,"transform":{}}],"name":"leg_right"},{"frame":[{"duration":4,"transform":{},"tweenEasing":0},{"duration":4,"transform":{"scX":0.8,"y":36.9454,"x":-1.6231},"tweenEasing":0},{"duration":0,"transform":{}}],"name":"leg_left"},{"frame":[{"duration":4,"transform":{},"tweenEasing":0},{"duration":4,"transform":{"y":17.1587,"skX":3.9811,"skY":3.9811},"tweenEasing":0},{"duration":0,"transform":{}}],"name":"hearth_2"},{"frame":[{"duration":8,"transform":{}}],"name":"braco"},{"frame":[{"duration":8,"transform":{}}],"name":"punho"},{"frame":[{"duration":4,"transform":{},"tweenEasing":0},{"duration":4,"transform":{"y":23.342,"skX":-1.8894,"skY":-1.8894},"tweenEasing":0},{"duration":0,"transform":{}}],"name":"hearth_1"}],"slot":[{"frame":[{"tweenEasing":0,"duration":8},{"tweenEasing":null,"duration":0}],"name":"leg_left"},{"frame":[{"tweenEasing":0,"duration":4},{"tweenEasing":0,"duration":4},{"tweenEasing":null,"duration":0}],"name":"hearth_2"},{"frame":[{"tweenEasing":null,"duration":8,"displayIndex":-1}],"name":"braco"},{"frame":[{"tweenEasing":0,"duration":8},{"tweenEasing":null,"duration":0}],"name":"hearth_1"},{"frame":[{"tweenEasing":null,"duration":8,"displayIndex":-1}],"name":"punho"},{"frame":[{"tweenEasing":0,"duration":8},{"tweenEasing":null,"duration":0}],"name":"leg_right"}],"ffd":[],"ik":[],"playTimes":0,"name":"idle"},{"duration":9,"frame":[],"bone":[{"frame":[{"duration":9,"transform":{}}],"name":"root"},{"frame":[{"duration":9,"transform":{}}],"name":"leg_right"},{"frame":[{"duration":9,"transform":{}}],"name":"leg_left"},{"frame":[{"duration":4,"transform":{},"tweenEasing":0},{"duration":5,"transform":{"skX":3.8831,"skY":3.8831}}],"name":"hearth_2"},{"frame":[{"duration":4,"transform":{"x":-52.9965},"tweenEasing":0},{"duration":5,"transform":{"scX":4.6923,"x":-52.9965}}],"name":"braco"},{"frame":[{"duration":4,"transform":{"x":-178.6933},"tweenEasing":0},{"duration":5,"transform":{"x":218.7804},"tweenEasing":0},{"duration":0,"transform":{"x":156.6472}}],"name":"punho"},{"frame":[{"duration":4,"transform":{},"tweenEasing":0},{"duration":5,"transform":{"skX":-4.4019,"skY":-4.4019}}],"name":"hearth_1"}],"slot":[{"frame":[{"tweenEasing":null,"duration":9}],"name":"leg_left"},{"frame":[{"tweenEasing":null,"duration":9}],"name":"hearth_2"},{"frame":[{"tweenEasing":null,"duration":9}],"name":"braco"},{"frame":[{"tweenEasing":null,"duration":9}],"name":"hearth_1"},{"frame":[{"tweenEasing":null,"duration":9}],"name":"punho"},{"frame":[{"tweenEasing":null,"duration":9}],"name":"leg_right"}],"ffd":[],"ik":[],"playTimes":0,"name":"punsh"},{"duration":12,"frame":[],"bone":[{"frame":[{"duration":12,"transform":{}}],"name":"root"},{"frame":[{"duration":4,"transform":{},"tweenEasing":0},{"duration":4,"transform":{"y":-16.139,"skX":-26.0999,"skY":-26.0999,"x":-53.3221},"tweenEasing":0},{"duration":2,"transform":{"y":121.5175,"skX":-90.3018,"skY":-90.3018,"x":-178.2942},"tweenEasing":0},{"duration":2,"transform":{"y":107.2772,"skX":-122.4028,"skY":-122.4028,"x":-160.9157},"tweenEasing":0},{"duration":0,"transform":{"y":127.8465,"skX":-94.9658,"skY":-94.9658,"x":-171.9915}}],"name":"leg_right"},{"frame":[{"duration":4,"transform":{},"tweenEasing":0},{"duration":4,"transform":{"y":-15.8226,"skX":-53.1437,"skY":-53.1437,"x":-69.4612},"tweenEasing":0},{"duration":2,"transform":{"y":77.8999,"skX":-100.3492,"skY":-100.3492,"x":-193.9322},"tweenEasing":0},{"duration":2,"transform":{"y":76.344,"skX":-123.952,"skY":-123.952,"x":-184.9661},"tweenEasing":0},{"duration":0,"transform":{"y":76.344,"skX":-78.4182,"skY":-78.4182,"x":-199.2064}}],"name":"leg_left"},{"frame":[{"duration":4,"transform":{},"tweenEasing":0},{"duration":4,"transform":{"y":-19.5409,"skX":8.4549,"skY":8.4549,"x":-81.0908},"tweenEasing":0},{"duration":2,"transform":{"y":99.1285,"skX":-23.6951,"skY":-23.6951,"x":-182.5136},"tweenEasing":0},{"duration":2,"transform":{"y":69.0656,"skX":-18.7573,"skY":-18.7573,"x":-182.5136},"tweenEasing":0},{"duration":0,"transform":{"y":100.7108,"skX":-25.6671,"skY":-25.6671,"x":-182.5136}}],"name":"hearth_2"},{"frame":[{"duration":12,"transform":{}}],"name":"braco"},{"frame":[{"duration":12,"transform":{}}],"name":"punho"},{"frame":[{"duration":4,"transform":{},"tweenEasing":0},{"duration":4,"transform":{"y":-22.7054,"skX":-4.499,"skY":-4.499,"x":-58.7809},"tweenEasing":0},{"duration":2,"transform":{"y":89.635,"skX":-39.0897,"skY":-39.0897,"x":-180.6149},"tweenEasing":0},{"duration":2,"transform":{"y":57.9898,"skX":-31.091,"skY":-31.091,"x":-180.6149},"tweenEasing":0},{"duration":0,"transform":{"y":100.7108,"skX":-40.6888,"skY":-40.6888,"x":-180.6149}}],"name":"hearth_1"}],"slot":[{"frame":[{"tweenEasing":0,"duration":4},{"tweenEasing":null,"duration":8,"color":{"rM":41,"bM":30,"gM":30}}],"name":"leg_left"},{"frame":[{"tweenEasing":0,"duration":4},{"tweenEasing":null,"duration":8,"displayIndex":1,"color":{"rM":41,"bM":30,"gM":30}}],"name":"hearth_2"},{"frame":[{"tweenEasing":null,"duration":12,"displayIndex":-1}],"name":"braco"},{"frame":[{"tweenEasing":0,"duration":4},{"tweenEasing":null,"duration":8,"displayIndex":1,"color":{"rM":41,"bM":30,"gM":30}}],"name":"hearth_1"},{"frame":[{"tweenEasing":null,"duration":12,"displayIndex":-1}],"name":"punho"},{"frame":[{"tweenEasing":0,"duration":4},{"tweenEasing":0,"duration":6,"color":{"rM":41,"bM":30,"gM":30}},{"tweenEasing":0,"duration":2,"color":{"rM":41,"bM":30,"gM":30}},{"tweenEasing":null,"duration":0,"color":{"rM":41,"bM":30,"gM":30}}],"name":"leg_right"}],"ffd":[],"ik":[],"playTimes":0,"name":"dying"}],"defaultActions":[{"gotoAndPlay":"idle"}],"name":"Armature","frameRate":24,"skin":[{"name":"","slot":[{"display":[{"path":"hearth_1","type":"image","name":"hearth_1","transform":{"y":-64.2103,"skX":113.5787,"skY":113.5787,"x":167.2479}},{"path":"hearth_1_die","type":"image","name":"hearth_1_die","transform":{"y":-64.21,"skX":113.58,"skY":113.58,"x":167.25}}],"name":"hearth_1"},{"display":[{"path":"braco","type":"image","name":"braco","transform":{"y":1.5536,"skX":-0.8371,"skY":-0.8371,"x":54.5285}}],"name":"braco"},{"display":[{"path":"leg_right","type":"image","name":"leg_right","transform":{"y":30.5324,"skX":-66.8105,"skY":-66.8105,"x":101.3668}}],"name":"leg_right"},{"display":[{"path":"punho","type":"image","name":"punho","transform":{"y":1.3981,"skX":6.5608,"skY":6.5608,"x":73.4211}}],"name":"punho"},{"display":[{"path":"leg_left","type":"image","name":"leg_left","transform":{"y":5.3572,"skX":-67.1163,"skY":-67.1163,"x":71.7107}}],"name":"leg_left"},{"display":[{"path":"hearth_2","type":"image","name":"hearth_2","transform":{"y":38.4564,"skX":101.9409,"skY":101.9409,"x":118.0476}},{"path":"hearth_2_die","type":"image","name":"hearth_2_die","transform":{"y":38.46,"skX":101.94,"skY":101.94,"x":118.05}}],"name":"hearth_2"}]}]}],"name":"hearth","version":"4.5"}